GitHelper
