Metadata-Version: 1.0
Name: git-helper
Version: 1.0.6
Summary: a git tool to push for multi projects
Home-page: https://github.com/Sidfate/GitHelper
Author: sidfate
Author-email: sidfate@163.com
License: MIT License
Keywords: git
Platform: any
